MyDataMemory.v
// Data memory module

module MyDataMemory (
    input wire clk,                   // Clock signal
    input wire mem_write,             // Memory write enable
    input wire [31:0] address,        // Memory address
    input wire [31:0] write_data,     // Data to write to memory
    output wire [31:0] read_data       // Data read from memory
);

    // Declare the data memory as an array of 256 words (32 bits each)
    // but why 256? because 2^8 = 256, and we are using 8 bits for addressing words in 32-bit words (4 bytes each)
    reg [31:0] memory [255:0];

    assign read_data = memory[address[31:2]]; // Word-aligned 

    integer i;

    // necessary to initialize memory to zero
    initial begin
        for (i=0; i<256; i=i+1)
            memory[i] = 0;
    end

    // Synchronous write operation
    always @(posedge clk) begin
        if (mem_write) begin
            memory[address[31:2]] <= write_data;
        end
    end
endmodule

MyAdder.v
// Simple adder. Uses 32-bit inputs and outputs their sum. Combinational logic to support carry over.
// parametrized width for future bit scalability.

module MyAdder #(parameter WIDTH = 32)(
    input [WIDTH-1:0] a,
    input [WIDTH-1:0] b,
    output [WIDTH-1:0] sum
);
    assign sum = a + b;
endmodule

MyAlu.v
// ALU Module. It uses the register with the given control signals to perform operations.

module MyALU(
    input wire [3:0] alu_control,
    input wire [31:0] operand_a,
    input wire [31:0] operand_b,
    output reg [31:0] alu_result,
    output zero
);
    assign zero = (alu_result == 32'b0);

    always @(*) begin
        case (alu_control)
            // ADD / ADDI / LW / SW: Funct3=000, Funct7[5]=0
            4'b0000: alu_result = operand_a + operand_b;  
            
            // SUB (alternative code): Funct3=000, Funct7[5]=1
            4'b0001: alu_result = operand_a - operand_b;
            
            // SLL / SLLI: Funct3=001, Funct7[5]=0
            4'b0010: alu_result = operand_a << operand_b[4:0]; 
            
            // SLT: Funct3=010, Funct7[5]=0
            4'b0100: alu_result = ($signed(operand_a) < $signed(operand_b)) ? 32'b1 : 32'b0;
            
            // SLTU: Funct3=011, Funct7[5]=0
            4'b0110: alu_result = (operand_a < operand_b) ? 32'b1 : 32'b0;
            
            // XOR: Funct3=100, Funct7[5]=0
            4'b1000: alu_result = operand_a ^ operand_b; 

            // SRL / SRLI: Funct3=101, Funct7[5]=0
            4'b1010: alu_result = operand_a >> operand_b[4:0];

            // SRA / SRAI: Funct3=101, Funct7[5]=1
            4'b1011: alu_result = $signed(operand_a) >>> operand_b[4:0];

            // OR: Funct3=110, Funct7[5]=0
            4'b1100: alu_result = operand_a | operand_b; 

            // AND: Funct3=111, Funct7[5]=0
            4'b1110: alu_result = operand_a & operand_b; 
            
            
            default: alu_result = 32'b0;
        endcase
    end
endmodule

MyALUControl.v
module MyALUControl(
    input [1:0] alu_op,
    input [2:0] funct3,
    input funct7,
    output reg [3:0] alu_ctrl_in
);
    always @(*) begin
        case (alu_op)
            2'b00: alu_ctrl_in = 4'b0000; // LW, SW -> Force ADD 
            2'b01: alu_ctrl_in = 4'b0001; // BEQ -> Force SUB 
            2'b10: begin // R-type AND I-Type
                case (funct3)
                    3'b000: alu_ctrl_in = (funct7) ? 4'b0001 : 4'b0000; // SUB : ADD
                    3'b001: alu_ctrl_in = 4'b0010; // SLL / SLLI
                    3'b010: alu_ctrl_in = 4'b0100; // SLT
                    3'b011: alu_ctrl_in = 4'b0110; // SLTU
                    3'b100: alu_ctrl_in = 4'b1000; // XOR
                    3'b101: alu_ctrl_in = (funct7) ? 4'b1011 : 4'b1010; // SRA : SRL
                    3'b110: alu_ctrl_in = 4'b1100; // OR
                    3'b111: alu_ctrl_in = 4'b1110; // AND
                    default: alu_ctrl_in = 4'b0000;
                endcase
            end
            default: alu_ctrl_in = 4'b0000;
        endcase
    end
endmodule

MyMultiplexer.v
// 32-bit MUX from register file to ALU (2-to-1)
// parametrized for bit scalability
module MyMultiplexer #(parameter WIDTH = 32)(
    input wire sel,                   // Select signal
    input wire [WIDTH-1:0] reg_data,      // Data from register file
    input wire [WIDTH-1:0] sign_ext,       // Data from program counter
    output wire [WIDTH-1:0] mux_out       // Output to ALU
);
    assign mux_out = (sel) ? sign_ext : reg_data;
endmodule

MySignExt.v
// the sign extension module for immediate values in RISC-V instructions

module MySignExt(
    input [31:0] instruction,
    output reg [31:0] imm_out
);

    wire [6:0] opcode;
    assign opcode = instruction[6:0];

    always @(*) begin
        case (opcode)
            // I-Type (LW) and I-Type Arithmetic (ADDI)
            7'b0000011, 7'b0010011: begin 
                // Sign-extend bit 31 to the top 20 bits, then take instr[31:20]
                imm_out = {{20{instruction[31]}}, instruction[31:20]};
            end

            7'b0100011: // SW
            begin
                // S-type immediate
                imm_out = {{20{instruction[31]}}, instruction[31:25], instruction[11:7]};
            end

            7'b1100011: // Branch
            begin
                // B-type immediate
                imm_out = {{20{instruction[31]}}, instruction[7], instruction[30:25], instruction[11:8], 1'b0};
            end

            7'b1101111: // JAL
            begin
                // J-type immediate
                imm_out = {{12{instruction[31]}}, instruction[19:12], instruction[20], instruction[30:21], 1'b0};
            end

            // LUI (U-Type)
            7'b0110111: begin
                imm_out = {instruction[31:12], 12'b0};
            end

            default:
            begin
                imm_out = 32'b0; // Default case
            end
        endcase
    end
endmodule

MyRegisterFile.v
// The 32-bit register file module

module MyRegisterFile #(parameter WIDTH = 32)(
    input clk,                  // Clock signal
    input wire [4:0] rs1_sel,     // Fireg_write_en read register address
    input wire [4:0] rs2_sel,     // Second read register address
    input wire [4:0] rd_reg,     // Write register address
    input wire [WIDTH-1:0] write_data,    // Data to write
    input wire reg_write,            // Write enable signal
    output wire [WIDTH-1:0] read_data1,   // Data from fireg_write_en read register
    output wire [WIDTH-1:0] read_data2    // Data from second read register
);

    // Declare the register file as an array of 32 registers, each 32 bits wide in RISCV32
    reg [WIDTH-1:0] registers [0:31];

    // Read operations (combinational logic)
    assign read_data1 = (rs1_sel == 5'b0) ? {WIDTH{1'b0}} : registers[rs1_sel];
    assign read_data2 = (rs2_sel == 5'b0) ? {WIDTH{1'b0}} : registers[rs2_sel];
    // Need this, otherwise, longer simulations may have X values
    integer i;
    
    initial begin
        for (i = 0; i < 32; i = i + 1)
            registers[i] = {WIDTH{1'b0}};
    end

    // Write operation (synchronous)
    always @(posedge clk) begin
        if (reg_write && (rd_reg != 5'b0)) begin
            registers[rd_reg] <= write_data;
        end
    end
endmodule

MyControlUnit.v
module MyControlUnit(
    // 7-bit opcode from instruction
    input [6:0] opcode,
    output reg branch,
    output reg [1:0] alu_op,
    output reg mem_read,
    output reg [1:0] mem_to_reg,
    output reg mem_write,
    output reg alu_src,
    output reg reg_write,
    output reg jump,
    output reg is_lui
);

    always @(*) begin
        // reset values of all control signals
        branch = 0;
        mem_read = 0;
        mem_to_reg = 0;
        alu_op = 2'b00;
        mem_write = 0;
        alu_src = 0;
        reg_write = 0;
        is_lui = 0; 
        jump = 0; 
        mem_to_reg = 2'b00;

        case (opcode)
        // includes all types. Signals are set accordingly.
            7'b0100011: begin // SW
                alu_src   = 1; // Address = Reg + Imm
                mem_write = 1; // WRITE to memory
                alu_op    = 2'b00; // Force ADD (Address calculation)

            end
            7'b0000011: begin // LW
                alu_src    = 1; // Operand B comes from Imm
                mem_to_reg = 2'b01; // Data comes from Memory, not ALU
                reg_write  = 1;
                mem_read   = 1;
                alu_op     = 2'b00; // Force ADD (Address calculation)
            end
            7'b1100011: begin // Branch
                branch  = 1;
                alu_op  = 2'b01; // Force SUB (to compare A and B)
            end
            7'b0110011: begin // R-type
                reg_write = 1;
                alu_op    = 2'b10; // "10" tells ALU Decoder to look at funct3/7
            end
            // I-Type Arithmetic (ADDI)
            7'b0010011: begin // I-Type Arithmetic (ADDI, ANDI, ORI, etc.)
            alu_src   = 1; // Use Immediate
            reg_write = 1; 
            alu_op    = 2'b10;
            end

            // LUI (U-Type)
            7'b0110111: begin 
                reg_write = 1;
                alu_src = 1;    // Use Imm
                is_lui = 1;     // NEW: Tells Top Level to zero out Operand A
                alu_op = 2'b00; // Force ADD (0 + Imm)
            end

            // JAL (J-Type)
            7'b1101111: begin 
                jump = 1;           // NEW: Force PC Jump
                reg_write = 1;      // Write return address
                mem_to_reg = 2'b10; // NEW: Select PC+4 to write back
                // alu_op doesn't matter, we don't use ALU result
            end

            default: begin
                // default case: all control signals are already set to 0
            end
        endcase
    end
endmodule

MyInstructionMemory.v
// The instruction memory module

module MyInstructionMemory (
    input wire [31:0] address,       
    output wire [31:0] instruction     
);

    // again, declare the instruction memory as an array of 256 words (32 bits each)
    reg [31:0] mem [0:255];

    // correct word alignment
    assign instruction = mem[address[31:2]]; 

    initial begin
        // program.hex will always be our test program! (can change the file in the directory, but keep the name)
        // logically not synthesizable, but it is necessary for the simulation
        $readmemh("program.hex", mem);
    end
endmodule

MyProgramCounter.v
// The program counter module

module MyProgramCounter #(parameter WIDTH = 32)(
    input wire clk,
    input wire rst,
    input [WIDTH-1:0] pc_in,
    output reg [WIDTH-1:0] pc_out
);

    // Synchronous process (sequential logic) to update the program counter
    always @(posedge clk or posedge rst) begin
        if (rst)
            pc_out <= {WIDTH{1'b0}}; // Reset program counter to 0
        else
            pc_out <= pc_in; // Update program counter with input value
    end
endmodule

MyProcessor.v
`timescale 1ns / 1ps

module MyProcessor (
    input wire clk,
    input wire rst
);

    // define PC & the Instruction variable
    wire [31:0] pc_current, pc_next, pc_plus_4, instruction;

    // address wires for branch and jump targets
    wire [31:0] branch_target_addr, jump_target_addr;

    // Signals for decoding instruction fields (see man)
    wire [6:0] opcode      = instruction[6:0];
    wire [4:0] rd_sel      = instruction[11:7];
    wire [2:0] funct3      = instruction[14:12];
    wire [4:0] rs1_sel     = instruction[19:15];
    wire [4:0] rs2_sel     = instruction[24:20];
    wire [6:0] funct7      = instruction[31:25];
    wire       funct7_b5   = instruction[30];

    // outputs of the control unit
    wire branch, mem_read, mem_write, reg_write, alu_src, jump, is_lui;
    wire [1:0] alu_op;
    wire [1:0] mem_to_reg; // Expanded to 2 bits for JAL support

    // Data Path Wires
    wire [31:0] rs1_data, rs2_data; // From RegFile
    wire [31:0] imm_out;            // From ImmGen
    wire [31:0] alu_operand_a;      // Actual input to ALU A (Handles LUI)
    wire [31:0] alu_operand_b;      // Actual input to ALU B (Handles ALUSrc)
    wire [3:0]  alu_control_sig;    // From ALU Control
    wire [31:0] alu_result;         // From ALU
    wire        zero_flag;          // From ALU (for BEQ)
    wire [31:0] mem_read_data;      // From Data Memory
    wire [31:0] write_back_data;    // Data written back to RegFile

    // Program Counter Register
    MyProgramCounter PC_Unit (
        .clk(clk),
        .rst(rst),
        .pc_in(pc_next),
        .pc_out(pc_current)
    );

    // PC + 4 Adder (four bits to next instruction)
    MyAdder Add_4_Unit (
        .a(pc_current),
        .b(32'd4),
        .sum(pc_plus_4)
    );

    // Instruction Memory
    MyInstructionMemory Instr_Mem (
        .address(pc_current),
        .instruction(instruction)
    );


    // Main Control Unit
    MyControlUnit Controller (
        .opcode(opcode),
        .branch(branch),
        .mem_read(mem_read),
        .mem_to_reg(mem_to_reg), // Expanded to 2 bits for JAL support
        .alu_op(alu_op),
        .mem_write(mem_write),
        .alu_src(alu_src),
        .reg_write(reg_write),
        .jump(jump),             
        .is_lui(is_lui)      
    );

    // Register File
    MyRegisterFile Reg_File (
        .clk(clk),
        .reg_write(reg_write),
        .rs1_sel(rs1_sel),
        .rs2_sel(rs2_sel),
        .rd_reg(rd_sel),
        .write_data(write_back_data),
        .read_data1(rs1_data),
        .read_data2(rs2_data)
    );

    // Immediate Generator (sign extension)
    MySignExt Imm_Gen (
        .instruction(instruction),
        .imm_out(imm_out)
    );


    // LUI Mux (Select 0 or RS1)
    MyMultiplexer LUI_Mux_Unit (
        .sel(is_lui),
        .reg_data(rs1_data),    // Input 0 (Normal)
        .sign_ext(32'b0),       // Input 1 (LUI case)
        .mux_out(alu_operand_a)
    );

    // ALU Src Mux (Select RS2 or Imm)
    MyMultiplexer ALUSrc_Mux_Unit (
        .sel(alu_src),
        .reg_data(rs2_data),    // Input 0
        .sign_ext(imm_out),     // Input 1
        .mux_out(alu_operand_b)
    );

    // ALU Control Decoder
    MyALUControl ALU_Dec (
        .alu_op(alu_op),
        .funct3(funct3),
        .funct7(funct7_b5), // Only bit 30 matters 
        .alu_ctrl_in(alu_control_sig)
    );

    // ALU
    MyALU Main_ALU (
        .alu_control(alu_control_sig),
        .operand_a(alu_operand_a),
        .operand_b(alu_operand_b),
        .alu_result(alu_result),
        .zero(zero_flag)
    );

    // Branch Target Calculator (PC + Imm)
    MyAdder Branch_Addr_Calc (
        .a(pc_current),
        .b(imm_out),
        .sum(branch_target_addr)
    );

    MyDataMemory Data_Mem (
        .clk(clk),
        .mem_write(mem_write),
        .address(alu_result),
        .write_data(rs2_data), // Store data always comes from RS2
        .read_data(mem_read_data)
    );

    // Write Back Mux (Handles JAL PC+4 logic)
    assign write_back_data = (mem_to_reg == 2'b00) ? alu_result :
                             (mem_to_reg == 2'b01) ? mem_read_data :
                             (mem_to_reg == 2'b10) ? pc_plus_4 : 32'b0;
    
    wire take_branch = branch & zero_flag;
    
    assign pc_next = (jump)        ? branch_target_addr : // JAL uses same math as Branch
                     (take_branch) ? branch_target_addr :
                                     pc_plus_4;

    // Now we are ready to do some synthesis and simulation

endmodule

riscv-tb.v
`timescale 1ns / 1ps

module RISCV_tb;

    reg clk;
    reg rst;

    MyProcessor uut (
        .clk(clk),
        .rst(rst)
    );

    // clock Generation
    initial begin
        clk = 0;
        forever #5 clk = ~clk;
    end

    // test Sequence
    initial begin
        $dumpfile("cpu_wave.vcd");
        $dumpvars(0, RISCV_tb);

        // hard reset sequence
        rst = 1;
        #20;          // delay for 20 (time) units
        @(negedge clk); // Wait for a falling edge 
        rst = 0;      

        #2500;        // Run

        // testing results

        $display("FINAL REGISTER STATE");
        $display("x1 (Loop Count): %d", uut.Reg_File.registers[1]);
        $display("x2 (Limit):      %d", uut.Reg_File.registers[2]);
        $display("x3 (Pointer):    %d", uut.Reg_File.registers[3]);
        $display("x10 (Result):    %h", uut.Reg_File.registers[10]);

        
        // check mem values
        $display("CHECKING MEMORY (Mem[0]..Mem[4])");
        // We use a loop to print them, verifying x3 actually moved
        $display("Addr 0: %d", uut.Data_Mem.memory[0]);
        $display("Addr 4: %d", uut.Data_Mem.memory[1]);
        $display("Addr 8: %d", uut.Data_Mem.memory[2]);
        $display("Addr 12: %d", uut.Data_Mem.memory[3]);
        $display("Addr 16: %d", uut.Data_Mem.memory[4]);
        
        if (uut.Reg_File.registers[10] === 32'hdeadb000)
            $display("PASSED!!!!");
        else
            $display("FAILURE D:");
        
        $finish;
    end

endmodule

cpu_wave.vcd
$date
	Thu Dec  4 15:18:34 2025
$end
$version
	Icarus Verilog
$end
$timescale
	1ps
$end
$scope module RISCV_tb $end
$var reg 1 ! clk $end
$var reg 1 " rst $end
$scope module uut $end
$var wire 1 ! clk $end
$var wire 1 " rst $end
$var wire 1 # take_branch $end
$var wire 1 $ zero_flag $end
$var wire 32 % write_back_data [31:0] $end
$var wire 5 & rs2_sel [4:0] $end
$var wire 32 ' rs2_data [31:0] $end
$var wire 5 ( rs1_sel [4:0] $end
$var wire 32 ) rs1_data [31:0] $end
$var wire 1 * reg_write $end
$var wire 5 + rd_sel [4:0] $end
$var wire 32 , pc_plus_4 [31:0] $end
$var wire 32 - pc_next [31:0] $end
$var wire 32 . pc_current [31:0] $end
$var wire 7 / opcode [6:0] $end
$var wire 1 0 mem_write $end
$var wire 2 1 mem_to_reg [1:0] $end
$var wire 32 2 mem_read_data [31:0] $end
$var wire 1 3 mem_read $end
$var wire 1 4 jump $end
$var wire 1 5 is_lui $end
$var wire 32 6 instruction [31:0] $end
$var wire 32 7 imm_out [31:0] $end
$var wire 1 8 funct7_b5 $end
$var wire 7 9 funct7 [6:0] $end
$var wire 3 : funct3 [2:0] $end
$var wire 32 ; branch_target_addr [31:0] $end
$var wire 1 < branch $end
$var wire 1 = alu_src $end
$var wire 32 > alu_result [31:0] $end
$var wire 32 ? alu_operand_b [31:0] $end
$var wire 32 @ alu_operand_a [31:0] $end
$var wire 2 A alu_op [1:0] $end
$var wire 4 B alu_control_sig [3:0] $end
$scope module ALUSrc_Mux_Unit $end
$var wire 32 C sign_ext [31:0] $end
$var wire 1 = sel $end
$var wire 32 D reg_data [31:0] $end
$var wire 32 E mux_out [31:0] $end
$var parameter 32 F WIDTH $end
$upscope $end
$scope module ALU_Dec $end
$var wire 3 G funct3 [2:0] $end
$var wire 1 8 funct7 $end
$var wire 2 H alu_op [1:0] $end
$var reg 4 I alu_ctrl_in [3:0] $end
$upscope $end
$scope module Add_4_Unit $end
$var wire 32 J b [31:0] $end
$var wire 32 K sum [31:0] $end
$var wire 32 L a [31:0] $end
$var parameter 32 M WIDTH $end
$upscope $end
$scope module Branch_Addr_Calc $end
$var wire 32 N sum [31:0] $end
$var wire 32 O b [31:0] $end
$var wire 32 P a [31:0] $end
$var parameter 32 Q WIDTH $end
$upscope $end
$scope module Controller $end
$var wire 7 R opcode [6:0] $end
$var reg 2 S alu_op [1:0] $end
$var reg 1 = alu_src $end
$var reg 1 < branch $end
$var reg 1 5 is_lui $end
$var reg 1 4 jump $end
$var reg 1 3 mem_read $end
$var reg 2 T mem_to_reg [1:0] $end
$var reg 1 0 mem_write $end
$var reg 1 * reg_write $end
$upscope $end
$scope module Data_Mem $end
$var wire 1 ! clk $end
$var wire 1 0 mem_write $end
$var wire 32 U read_data [31:0] $end
$var wire 32 V write_data [31:0] $end
$var wire 32 W address [31:0] $end
$var integer 32 X i [31:0] $end
$upscope $end
$scope module Imm_Gen $end
$var wire 7 Y opcode [6:0] $end
$var wire 32 Z instruction [31:0] $end
$var reg 32 [ imm_out [31:0] $end
$upscope $end
$scope module Instr_Mem $end
$var wire 32 \ instruction [31:0] $end
$var wire 32 ] address [31:0] $end
$upscope $end
$scope module LUI_Mux_Unit $end
$var wire 1 5 sel $end
$var wire 32 ^ sign_ext [31:0] $end
$var wire 32 _ reg_data [31:0] $end
$var wire 32 ` mux_out [31:0] $end
$var parameter 32 a WIDTH $end
$upscope $end
$scope module Main_ALU $end
$var wire 4 b alu_control [3:0] $end
$var wire 32 c operand_a [31:0] $end
$var wire 32 d operand_b [31:0] $end
$var wire 1 $ zero $end
$var reg 32 e alu_result [31:0] $end
$upscope $end
$scope module PC_Unit $end
$var wire 1 ! clk $end
$var wire 32 f pc_in [31:0] $end
$var wire 1 " rst $end
$var parameter 32 g WIDTH $end
$var reg 32 h pc_out [31:0] $end
$upscope $end
$scope module Reg_File $end
$var wire 1 ! clk $end
$var wire 5 i rd_reg [4:0] $end
$var wire 1 * reg_write $end
$var wire 5 j rs1_sel [4:0] $end
$var wire 5 k rs2_sel [4:0] $end
$var wire 32 l write_data [31:0] $end
$var wire 32 m read_data2 [31:0] $end
$var wire 32 n read_data1 [31:0] $end
$var parameter 32 o WIDTH $end
$var integer 32 p i [31:0] $end
$upscope $end
$upscope $end
$upscope $end
$enddefinitions $end
$comment Show the parameter values. $end
$dumpall
b100000 o
b100000 g
b100000 a
b100000 Q
b100000 M
b100000 F
$end
#0
$dumpvars
b100000 p
b0 n
b0 m
b0 l
b0 k
b0 j
b1 i
b0 h
b100 f
b0 e
b0 d
b0 c
b0 b
b0 `
b0 _
b0 ^
b0 ]
b10010011 \
b0 [
b10010011 Z
b10011 Y
b100000000 X
b0 W
b0 V
b0 U
b0 T
b10 S
b10011 R
b0 P
b0 O
b0 N
b0 L
b100 K
b100 J
b0 I
b10 H
b0 G
b0 E
b0 D
b0 C
b0 B
b10 A
b0 @
b0 ?
b0 >
1=
0<
b0 ;
b0 :
b0 9
08
b0 7
b10010011 6
05
04
03
b0 2
b0 1
00
b10011 /
b0 .
b100 -
b100 ,
b1 +
1*
b0 )
b0 (
b0 '
b0 &
b0 %
1$
0#
1"
0!
$end
#5000
1!
#10000
0!
#15000
1!
#20000
0"
0!
#25000
b101 %
b101 l
0$
b101 >
b101 W
b101 e
b101 ?
b101 E
b101 d
b101 &
b101 k
b10 +
b10 i
b101 7
b101 C
b101 O
b101 [
b1000 -
b1000 f
b10100000000000100010011 6
b10100000000000100010011 Z
b10100000000000100010011 \
b1001 ;
b1001 N
b1000 ,
b1000 K
b100 .
b100 L
b100 P
b100 ]
b100 h
1!
#30000
0!
#35000
b0 %
b0 l
1$
b0 >
b0 W
b0 e
b0 ?
b0 E
b0 d
b0 &
b0 k
b11 +
b11 i
b0 7
b0 C
b0 O
b0 [
b1100 -
b1100 f
b110010011 6
b110010011 Z
b110010011 \
b1000 ;
b1000 N
b1100 ,
b1100 K
b1000 .
b1000 L
b1000 P
b1000 ]
b1000 h
1!
#40000
0!
#45000
bx 2
bx U
b11111111111111111111111111111011 %
b11111111111111111111111111111011 l
b1 B
b1 I
b1 b
0$
b11111111111111111111111111111011 >
b11111111111111111111111111111011 W
b11111111111111111111111111111011 e
b101 '
b101 D
b101 V
b101 m
1<
0*
0=
b1 A
b1 H
b1 S
b101 ?
b101 E
b101 d
b1100011 Y
b1 9
b10 &
b10 k
b1 (
b1 j
b100 +
b100 i
b1100011 /
b1100011 R
b100100 7
b100100 C
b100100 O
b100100 [
b10000 -
b10000 f
b10001000001000001001100011 6
b10001000001000001001100011 Z
b10001000001000001001100011 \
b110000 ;
b110000 N
b10000 ,
b10000 K
b1100 .
b1100 L
b1100 P
b1100 ]
b1100 h
1!
#50000
0!
#55000
b0 2
b0 U
b1010 %
b1010 l
b1010 >
b1010 W
b1010 e
b1010 ?
b1010 E
b1010 d
b0 B
b0 I
b0 b
b0 '
b0 D
b0 V
b0 m
1*
1=
b10 A
b10 H
b10 S
0<
b10011 Y
b0 9
b1010 &
b1010 k
b10011 /
b10011 R
b1010 7
b1010 C
b1010 O
b1010 [
b10100 -
b10100 f
b101000001000001000010011 6
b101000001000001000010011 Z
b101000001000001000010011 \
b11010 ;
b11010 N
b10100 ,
b10100 K
b10000 .
b10000 L
b10000 P
b10000 ]
b10000 h
1!
#60000
0!
#65000
b10100 %
b10100 l
b1010 @
b1010 `
b1010 c
0$
b10100 >
b10100 W
b10100 e
b1010 )
b1010 _
b1010 n
b10 B
b10 I
b10 b
b1 ?
b1 E
b1 d
b1 &
b1 k
b100 (
b100 j
b1 :
b1 G
b101 +
b101 i
b1 7
b1 C
b1 O
b1 [
b11000 -
b11000 f
b100100001001010010011 6
b100100001001010010011 Z
b100100001001010010011 \
b10101 ;
b10101 N
b11000 ,
b11000 K
b10100 .
b10100 L
b10100 P
b10100 ]
b10100 h
1!
#70000
0!
#75000
b101 %
b101 l
b0 @
b0 `
b0 c
b101 >
b101 W
b101 e
b101 '
b101 D
b101 V
b101 m
b0 )
b0 _
b0 n
b1100 B
b1100 I
b1100 b
1*
0=
b10 A
b10 H
b10 S
b101 ?
b101 E
b101 d
b110011 Y
b10 &
b10 k
b1 (
b1 j
b110 :
b110 G
b110 +
b110 i
b110011 /
b110011 R
b0 7
b0 C
b0 O
b0 [
b11100 -
b11100 f
b1000001110001100110011 6
b1000001110001100110011 Z
b1000001110001100110011 \
b11000 ;
b11000 N
b11100 ,
b11100 K
b11000 .
b11000 L
b11000 P
b11000 ]
b11000 h
1!
#80000
0!
#85000
b0 %
b0 l
1$
b0 >
b0 W
b0 e
b0 ?
b0 E
b0 d
b10100 '
b10100 D
b10100 V
b10100 m
b0 B
b0 I
b0 b
10
1=
0*
b0 A
b0 H
b0 S
b100011 Y
b101 &
b101 k
b11 (
b11 j
b10 :
b10 G
b0 +
b0 i
b100011 /
b100011 R
b100000 -
b100000 f
b10100011010000000100011 6
b10100011010000000100011 Z
b10100011010000000100011 \
b11100 ;
b11100 N
b100000 ,
b100000 K
b11100 .
b11100 L
b11100 P
b11100 ]
b11100 h
1!
#90000
0!
#95000
b10100 %
b10100 l
1$
b0 >
b0 W
b0 e
b0 '
b0 D
b0 V
b0 m
13
1*
b1 1
b1 T
1=
00
b0 ?
b0 E
b0 d
b11 Y
b0 &
b0 k
b111 +
b111 i
b11 /
b11 R
b0 7
b0 C
b0 O
b0 [
b100100 -
b100100 f
b11010001110000011 6
b11010001110000011 Z
b11010001110000011 \
b10100 2
b10100 U
b100000 ;
b100000 N
b100100 ,
b100100 K
b100000 .
b100000 L
b100000 P
b100000 ]
b100000 h
1!
#100000
0!
#105000
b1 %
b1 l
0$
b1 >
b1 W
b1 e
b10 A
b10 H
b10 S
1*
1=
b0 1
b0 T
03
b1 ?
b1 E
b1 d
b10011 Y
b1 &
b1 k
b1 (
b1 j
b0 :
b0 G
b1 +
b1 i
b10011 /
b10011 R
b1 7
b1 C
b1 O
b1 [
b101000 -
b101000 f
b100001000000010010011 6
b100001000000010010011 Z
b100001000000010010011 \
b100101 ;
b100101 N
b101000 ,
b101000 K
b100100 .
b100100 L
b100100 P
b100100 ]
b100100 h
1!
#110000
0!
#115000
b0 2
b0 U
b100 %
b100 l
b100 >
b100 W
b100 e
b100 ?
b100 E
b100 d
b0 @
b0 `
b0 c
b100 &
b100 k
b11 (
b11 j
b11 +
b11 i
b100 7
b100 C
b100 O
b100 [
b101100 -
b101100 f
b0 )
b0 _
b0 n
b1010 '
b1010 D
b1010 V
b1010 m
b10000011000000110010011 6
b10000011000000110010011 Z
b10000011000000110010011 \
b101100 ;
b101100 N
b101100 ,
b101100 K
b101000 .
b101000 L
b101000 P
b101000 ]
b101000 h
1!
#120000
0!
#125000
b10100 2
b10100 U
b110000 %
b110000 l
b1 >
b1 W
b1 e
b1 '
b1 D
b1 V
b1 m
b10 1
b10 T
14
1*
0=
b0 A
b0 H
b0 S
b1 ?
b1 E
b1 d
b0 @
b0 `
b0 c
b1101111 Y
18
b1111111 9
b1 &
b1 k
b11111 (
b11111 j
b111 :
b111 G
b0 +
b0 i
b1101111 /
b1101111 R
b11111111111111111111111111100000 7
b11111111111111111111111111100000 C
b11111111111111111111111111100000 O
b11111111111111111111111111100000 [
b1100 -
b1100 f
b0 )
b0 _
b0 n
b11111110000111111111000001101111 6
b11111110000111111111000001101111 Z
b11111110000111111111000001101111 \
b1100 ;
b1100 N
b110000 ,
b110000 K
b101100 .
b101100 L
b101100 P
b101100 ]
b101100 h
1!
#130000
0!
#135000
bx 2
bx U
b101 ?
b101 E
b101 d
b1 @
b1 `
b1 c
b11111111111111111111111111111100 >
b11111111111111111111111111111100 W
b11111111111111111111111111111100 e
b101 '
b101 D
b101 V
b101 m
b1 )
b1 _
b1 n
b1 B
b1 I
b1 b
b1 A
b1 H
b1 S
1<
04
0*
b0 1
b0 T
b11111111111111111111111111111100 %
b11111111111111111111111111111100 l
b1100011 Y
08
b1 9
b10 &
b10 k
b1 (
b1 j
b0 :
b0 G
b100 +
b100 i
b1100011 /
b1100011 R
b100100 7
b100100 C
b100100 O
b100100 [
b10001000001000001001100011 6
b10001000001000001001100011 Z
b10001000001000001001100011 \
b10000 -
b10000 f
b110000 ;
b110000 N
b10000 ,
b10000 K
b1100 .
b1100 L
b1100 P
b1100 ]
b1100 h
1!
#140000
0!
#145000
b0 2
b0 U
b1011 %
b1011 l
b1011 >
b1011 W
b1011 e
b1010 ?
b1010 E
b1010 d
b0 B
b0 I
b0 b
b0 '
b0 D
b0 V
b0 m
1*
1=
b10 A
b10 H
b10 S
0<
b10011 Y
b0 9
b1010 &
b1010 k
b10011 /
b10011 R
b1010 7
b1010 C
b1010 O
b1010 [
b10100 -
b10100 f
b101000001000001000010011 6
b101000001000001000010011 Z
b101000001000001000010011 \
b11010 ;
b11010 N
b10100 ,
b10100 K
b10000 .
b10000 L
b10000 P
b10000 ]
b10000 h
1!
#150000
0!
#155000
b0 2
b0 U
b10110 %
b10110 l
b1011 @
b1011 `
b1011 c
b10110 >
b10110 W
b10110 e
b1 '
b1 D
b1 V
b1 m
b1011 )
b1011 _
b1011 n
b10 B
b10 I
b10 b
b1 ?
b1 E
b1 d
b1 &
b1 k
b100 (
b100 j
b1 :
b1 G
b101 +
b101 i
b1 7
b1 C
b1 O
b1 [
b11000 -
b11000 f
b100100001001010010011 6
b100100001001010010011 Z
b100100001001010010011 \
b10101 ;
b10101 N
b11000 ,
b11000 K
b10100 .
b10100 L
b10100 P
b10100 ]
b10100 h
1!
#160000
0!
#165000
b101 %
b101 l
b1 @
b1 `
b1 c
b101 >
b101 W
b101 e
b101 '
b101 D
b101 V
b101 m
b1 )
b1 _
b1 n
b1100 B
b1100 I
b1100 b
1*
0=
b10 A
b10 H
b10 S
b101 ?
b101 E
b101 d
b110011 Y
b10 &
b10 k
b1 (
b1 j
b110 :
b110 G
b110 +
b110 i
b110011 /
b110011 R
b0 7
b0 C
b0 O
b0 [
b11100 -
b11100 f
b1000001110001100110011 6
b1000001110001100110011 Z
b1000001110001100110011 \
b11000 ;
b11000 N
b11100 ,
b11100 K
b11000 .
b11000 L
b11000 P
b11000 ]
b11000 h
1!
#170000
0!
#175000
b0 2
b0 U
b100 %
b100 l
b100 @
b100 `
b100 c
b100 >
b100 W
b100 e
b0 ?
b0 E
b0 d
b10110 '
b10110 D
b10110 V
b10110 m
b100 )
b100 _
b100 n
b0 B
b0 I
b0 b
10
1=
0*
b0 A
b0 H
b0 S
b100011 Y
b101 &
b101 k
b11 (
b11 j
b10 :
b10 G
b0 +
b0 i
b100011 /
b100011 R
b100000 -
b100000 f
b10100011010000000100011 6
b10100011010000000100011 Z
b10100011010000000100011 \
b11100 ;
b11100 N
b100000 ,
b100000 K
b11100 .
b11100 L
b11100 P
b11100 ]
b11100 h
1!
#180000
0!
